odoo/addons/sale_automatic_workflow_delivery_state/README.rst
odoo/addons/sale_automatic_workflow_delivery_state/__init__.py
odoo/addons/sale_automatic_workflow_delivery_state/__manifest__.py
odoo/addons/sale_automatic_workflow_delivery_state/i18n/sale_automatic_workflow_delivery_state.pot
odoo/addons/sale_automatic_workflow_delivery_state/models/sale_order.py
odoo/addons/sale_automatic_workflow_delivery_state/readme/DESCRIPTION.rst
odoo/addons/sale_automatic_workflow_delivery_state/readme/ROADMAP.rst
odoo/addons/sale_automatic_workflow_delivery_state/static/description/icon.png
odoo/addons/sale_automatic_workflow_delivery_state/static/description/index.html
odoo13_addon_sale_automatic_workflow_delivery_state-13.0.1.0.1.dist-info/METADATA
odoo13_addon_sale_automatic_workflow_delivery_state-13.0.1.0.1.dist-info/WHEEL
odoo13_addon_sale_automatic_workflow_delivery_state-13.0.1.0.1.dist-info/top_level.txt
odoo13_addon_sale_automatic_workflow_delivery_state-13.0.1.0.1.dist-info/RECORD
