Metadata-Version: 2.1
Name: odoo13-addon-sale-automatic-workflow-delivery-state
Version: 13.0.1.0.1
Summary: Glue module for sale_automatic_workflow and sale_delivery_state
Home-page: https://github.com/OCA/sale-workflow
Author: Akretion, Odoo Community Association (OCA)
Author-email: support@odoo-community.org
License: AGPL-3
Platform: UNKNOWN
Classifier: Programming Language :: Python
Classifier: Framework :: Odoo
Classifier: License :: OSI Approved :: GNU Affero General Public License v3
Requires-Python: >=3.5
Requires-Dist: odoo13-addon-sale-automatic-workflow
Requires-Dist: odoo13-addon-sale-delivery-state
Requires-Dist: odoo (<13.1dev,>=13.0a)
